codefly_sdk/__init__.py
codefly_sdk/codefly.py
codefly_sdk-0.0.14.dist-info/METADATA
codefly_sdk-0.0.14.dist-info/WHEEL
codefly_sdk-0.0.14.dist-info/RECORD
