Metadata-Version: 2.1
Name: codefly-sdk
Version: 0.0.14
Summary: 
Author: Antoine Toussaint
Author-email: antoine.toussaint@codefly.ai
Requires-Python: >=3.10,<4.0
Classifier: Programming Language :: Python :: 3
Classifier: Programming Language :: Python :: 3.10
Classifier: Programming Language :: Python :: 3.11
Classifier: Programming Language :: Python :: 3.12
Requires-Dist: PyYAML (>=6.0.1,<7.0.0)
Requires-Dist: pydantic (>=2.7.1,<3.0.0)
